<?xml version="1.0" encoding="utf-8" ?><dwsync><file name="accordion.less" server="41.203.21.102//var/www/prototypes/vumi/pub/www-app/" local="3412216630" remote="12002164097" /><file name="alerts.less" server="41.203.21.102//var/www/prototypes/vumi/pub/www-app/" local="3412216630" remote="12002164097" /><file name="bootstrap.less" server="41.203.21.102//var/www/prototypes/vumi/pub/www-app/" local="3412216630" remote="12002164097" /><file name="breadcrumbs.less" server="41.203.21.102//var/www/prototypes/vumi/pub/www-app/" local="3412216630" remote="12002164098" /><file name="button-groups.less" server="41.203.21.102//var/www/prototypes/vumi/pub/www-app/" local="3412216630" remote="12002164098" /><file name="buttons.less" server="41.203.21.102//var/www/prototypes/vumi/pub/www-app/" local="3412216630" remote="12002164098" /><file name="carousel.less" server="41.203.21.102//var/www/prototypes/vumi/pub/www-app/" local="3412216630" remote="12002164098" /><file name="close.less" server="41.203.21.102//var/www/prototypes/vumi/pub/www-app/" local="3412216630" remote="12002164098" /><file name="code.less" server="41.203.21.102//var/www/prototypes/vumi/pub/www-app/" local="3412216630" remote="12002164099" /><file name="component-animations.less" server="41.203.21.102//var/www/prototypes/vumi/pub/www-app/" local="3412216630" remote="12002164099" /><file name="dropdowns.less" server="41.203.21.102//var/www/prototypes/vumi/pub/www-app/" local="3412216630" remote="12002164099" /><file name="forms.less" server="41.203.21.102//var/www/prototypes/vumi/pub/www-app/" local="3412216630" remote="12002164100" /><file name="grid.less" server="41.203.21.102//var/www/prototypes/vumi/pub/www-app/" local="3412216630" remote="12002164100" /><file name="hero-unit.less" server="41.203.21.102//var/www/prototypes/vumi/pub/www-app/" local="3412229063" remote="12002164100" /><file name="labels.less" server="41.203.21.102//var/www/prototypes/vumi/pub/www-app/" local="3412216630" remote="12002164100" /><file name="layouts.less" server="41.203.21.102//var/www/prototypes/vumi/pub/www-app/" local="3412216630" remote="12002164101" /><file name="mixins.less" server="41.203.21.102//var/www/prototypes/vumi/pub/www-app/" local="3412216630" remote="12002164101" /><file name="modals.less" server="41.203.21.102//var/www/prototypes/vumi/pub/www-app/" local="3412216630" remote="12002164101" /><file name="navbar.less" server="41.203.21.102//var/www/prototypes/vumi/pub/www-app/" local="3412216630" remote="12002164102" /><file name="navs.less" server="41.203.21.102//var/www/prototypes/vumi/pub/www-app/" local="3412216630" remote="12002164102" /><file name="pager.less" server="41.203.21.102//var/www/prototypes/vumi/pub/www-app/" local="3412216630" remote="12002164102" /><file name="pagination.less" server="41.203.21.102//var/www/prototypes/vumi/pub/www-app/" local="3412216630" remote="12002164102" /><file name="patterns.less" server="41.203.21.102//var/www/prototypes/vumi/pub/www-app/" local="3412216630" remote="12002164102" /><file name="popovers.less" server="41.203.21.102//var/www/prototypes/vumi/pub/www-app/" local="3412216630" remote="12002164103" /><file name="print.less" server="41.203.21.102//var/www/prototypes/vumi/pub/www-app/" local="3412216630" remote="12002164103" /><file name="progress-bars.less" server="41.203.21.102//var/www/prototypes/vumi/pub/www-app/" local="3412216630" remote="12002164103" /><file name="reset.less" server="41.203.21.102//var/www/prototypes/vumi/pub/www-app/" local="3412216630" remote="12002164103" /><file name="responsive.less" server="41.203.21.102//var/www/prototypes/vumi/pub/www-app/" local="3412216630" remote="12002164104" /><file name="scaffolding.less" server="41.203.21.102//var/www/prototypes/vumi/pub/www-app/" local="3412216630" remote="12002164104" /><file name="sprites.less" server="41.203.21.102//var/www/prototypes/vumi/pub/www-app/" local="3412216630" remote="12002164104" /><file name="tables.less" server="41.203.21.102//var/www/prototypes/vumi/pub/www-app/" local="3412216630" remote="12002164104" /><file name="thumbnails.less" server="41.203.21.102//var/www/prototypes/vumi/pub/www-app/" local="3412216630" remote="12002164105" /><file name="tooltip.less" server="41.203.21.102//var/www/prototypes/vumi/pub/www-app/" local="3412216630" remote="12002164105" /><file name="type.less" server="41.203.21.102//var/www/prototypes/vumi/pub/www-app/" local="3412216630" remote="12002164105" /><file name="utilities.less" server="41.203.21.102//var/www/prototypes/vumi/pub/www-app/" local="3412216630" remote="12002164105" /><file name="variables.less" server="41.203.21.102//var/www/prototypes/vumi/pub/www-app/" local="3412216630" remote="12002164105" /><file name="wells.less" server="41.203.21.102//var/www/prototypes/vumi/pub/www-app/" local="3412216630" remote="12002164106" /><file name="accordion.less" server="www.praekelt.co.za//public_html/vumi-go/" local="3412216630" remote="12004688792" /><file name="alerts.less" server="www.praekelt.co.za//public_html/vumi-go/" local="3412216630" remote="12004688792" /><file name="bootstrap.less" server="www.praekelt.co.za//public_html/vumi-go/" local="3414252999" remote="12004688852" /><file name="breadcrumbs.less" server="www.praekelt.co.za//public_html/vumi-go/" local="3412216630" remote="12004688852" /><file name="button-groups.less" server="www.praekelt.co.za//public_html/vumi-go/" local="3412216630" remote="12004688852" /><file name="buttons.less" server="www.praekelt.co.za//public_html/vumi-go/" local="3412216630" remote="12004688852" /><file name="carousel.less" server="www.praekelt.co.za//public_html/vumi-go/" local="3412216630" remote="12004688852" /><file name="close.less" server="www.praekelt.co.za//public_html/vumi-go/" local="3412216630" remote="12004688852" /><file name="code.less" server="www.praekelt.co.za//public_html/vumi-go/" local="3412216630" remote="12004688852" /><file name="component-animations.less" server="www.praekelt.co.za//public_html/vumi-go/" local="3412216630" remote="12004688852" /><file name="dropdowns.less" server="www.praekelt.co.za//public_html/vumi-go/" local="3412216630" remote="12004688852" /><file name="font-awesome.less" server="www.praekelt.co.za//public_html/vumi-go/" local="3414253411" remote="12004688852" /><file name="forms.less" server="www.praekelt.co.za//public_html/vumi-go/" local="3412216630" remote="12004688852" /><file name="grid.less" server="www.praekelt.co.za//public_html/vumi-go/" local="3412216630" remote="12004688852" /><file name="hero-unit.less" server="www.praekelt.co.za//public_html/vumi-go/" local="3412229063" remote="12004688852" /><file name="labels.less" server="www.praekelt.co.za//public_html/vumi-go/" local="3412216630" remote="12004688852" /><file name="layouts.less" server="www.praekelt.co.za//public_html/vumi-go/" local="3412216630" remote="12004688852" /><file name="mixins.less" server="www.praekelt.co.za//public_html/vumi-go/" local="3412216630" remote="12004688852" /><file name="modals.less" server="www.praekelt.co.za//public_html/vumi-go/" local="3412216630" remote="12004688852" /><file name="navbar.less" server="www.praekelt.co.za//public_html/vumi-go/" local="3412216630" remote="12004688852" /><file name="navs.less" server="www.praekelt.co.za//public_html/vumi-go/" local="3412216630" remote="12004688852" /><file name="pager.less" server="www.praekelt.co.za//public_html/vumi-go/" local="3412216630" remote="12004688852" /><file name="pagination.less" server="www.praekelt.co.za//public_html/vumi-go/" local="3412216630" remote="12004688852" /><file name="patterns.less" server="www.praekelt.co.za//public_html/vumi-go/" local="3412216630" remote="12004688852" /><file name="popovers.less" server="www.praekelt.co.za//public_html/vumi-go/" local="3412216630" remote="12004688852" /><file name="print.less" server="www.praekelt.co.za//public_html/vumi-go/" local="3412216630" remote="12004688852" /><file name="progress-bars.less" server="www.praekelt.co.za//public_html/vumi-go/" local="3412216630" remote="12004688852" /><file name="reset.less" server="www.praekelt.co.za//public_html/vumi-go/" local="3412216630" remote="12004688852" /><file name="responsive.less" server="www.praekelt.co.za//public_html/vumi-go/" local="3412216630" remote="12004688852" /><file name="scaffolding.less" server="www.praekelt.co.za//public_html/vumi-go/" local="3412216630" remote="12004688852" /><file name="sprites.less" server="www.praekelt.co.za//public_html/vumi-go/" local="3412216630" remote="12004688852" /><file name="tables.less" server="www.praekelt.co.za//public_html/vumi-go/" local="3412216630" remote="12004688852" /><file name="thumbnails.less" server="www.praekelt.co.za//public_html/vumi-go/" local="3412216630" remote="12004688852" /><file name="tooltip.less" server="www.praekelt.co.za//public_html/vumi-go/" local="3412216630" remote="12004688852" /><file name="type.less" server="www.praekelt.co.za//public_html/vumi-go/" local="3412216630" remote="12004688852" /><file name="utilities.less" server="www.praekelt.co.za//public_html/vumi-go/" local="3412216630" remote="12004688852" /><file name="variables.less" server="www.praekelt.co.za//public_html/vumi-go/" local="3412216630" remote="12004688852" /><file name="wells.less" server="www.praekelt.co.za//public_html/vumi-go/" local="3412216630" remote="12004688852" /></dwsync>